snowlib/__init__.py
snowlib/context.py
snowlib/py.typed
snowlib/session.py
snowlib/sqlalchemy.py
snowlib/_data/connections.toml.example
snowlib/_data/test_config.toml.example
snowlib/connection/__init__.py
snowlib/connection/base.py
snowlib/connection/connection.py
snowlib/connection/paths.py
snowlib/connection/profiles.py
snowlib/models/__init__.py
snowlib/models/column.py
snowlib/models/database.py
snowlib/models/schema.py
snowlib/models/stage.py
snowlib/models/base/__init__.py
snowlib/models/base/core.py
snowlib/models/base/fqn.py
snowlib/models/base/schema_child.py
snowlib/models/base/show.py
snowlib/models/table/__init__.py
snowlib/models/table/base.py
snowlib/models/table/dynamic_table.py
snowlib/models/table/materialized_view.py
snowlib/models/table/table.py
snowlib/models/table/view.py
snowlib/primitives/__init__.py
snowlib/primitives/async_query.py
snowlib/primitives/execute.py
snowlib/primitives/result.py
snowlib/utils/identifiers.py
snowlib/utils/json_columns.py
snowlib/utils/query.py
snowlib/utils/schema.py
snowlib-0.4.7.dist-info/licenses/LICENSE
snowlib-0.4.7.dist-info/licenses/licenses/THIRD_PARTY.md
snowlib-0.4.7.dist-info/METADATA
snowlib-0.4.7.dist-info/WHEEL
snowlib-0.4.7.dist-info/top_level.txt
snowlib-0.4.7.dist-info/RECORD
